airflow_memray/__init__.py
airflow_memray/core.py
airflow_memray/plugin.py
airflow_memray/policies.py
airflow_memray-0.1.1.dist-info/licenses/LICENSE
dags/memray_demo.py
include/__init__.py
airflow_memray-0.1.1.dist-info/METADATA
airflow_memray-0.1.1.dist-info/WHEEL
airflow_memray-0.1.1.dist-info/entry_points.txt
airflow_memray-0.1.1.dist-info/top_level.txt
airflow_memray-0.1.1.dist-info/RECORD
