Metadata-Version: 2.4
Name: airflow-memray
Version: 0.1.1
Summary: Memory profiling for Airflow with Memray.
Author-email: Cedrik Neumann <7921017+m1racoli@users.noreply.github.com>
License: Apache License 2.0
Project-URL: Homepage, https://github.com/m1racoli/airflow-memray/
Project-URL: Source, https://github.com/m1racoli/airflow-memray/
Project-URL: Documentation, https://github.com/m1racoli/airflow-memray/
Project-URL: Changelog, https://github.com/m1racoli/airflow-memray/blob/main/CHANGELOG.md
Classifier: Development Status :: 3 - Alpha
Classifier: Framework :: Apache Airflow :: Provider
Classifier: Framework :: Apache Airflow
Classifier: Intended Audience :: Developers
Classifier: License :: OSI Approved :: Apache Software License
Classifier: Programming Language :: Python :: 3.11
Classifier: Programming Language :: Python :: 3
Requires-Python: ~=3.11
License-File: LICENSE
Requires-Dist: apache-airflow>=2.9
Requires-Dist: memray~=1.13
Dynamic: license-file
